MANIFEST.in
setup.py
django_debian/__init__.py
django_debian/config_file.py
django_debian/dbconfig.py
django_debian/secret_key.py
django_debian/settings.py
django_debian.egg-info/PKG-INFO
django_debian.egg-info/SOURCES.txt
django_debian.egg-info/dependency_links.txt
django_debian.egg-info/requires.txt
django_debian.egg-info/top_level.txt
django_debian.egg-info/zip-safe
dpkg/common
dpkg/config
dpkg/postinst
dpkg/postrm
dpkg/prerm
dpkg/rules
dpkg/webserver/apache2
dpkg/webserver/none