Metadata-Version: 1.0
Name: django-debian
Version: 0.10.2
Summary: Debian integration for Django applications
Home-page: http://launchpad.net/django-debian
Author: Zygmunt Krynicki
Author-email: zygmunt.krynicki@canonical.com
License: LGPL3
Platform: UNKNOWN
